kms/__init__.py
kms/bypass.py
kms/classes.py
kms/functions.py
kms/get_char_code.py
kms/hash.py
kms/ig.py
kms/list.py
kms/page_inspect.py
kms/sql.py
kms-1.0.1.3.dist-info/METADATA
kms-1.0.1.3.dist-info/WHEEL
kms-1.0.1.3.dist-info/top_level.txt
kms-1.0.1.3.dist-info/RECORD
