Metadata-Version: 2.1
Name: kms
Version: 1.0.1.3
Summary: A Hacking Library That Helps You To Create Hacking Tools.
Home-page: https://github.com/ArshiaPRG/kms
Author: Ar$h1a
Author-email: 1arhacker1@gmail.com
License: UNKNOWN
Platform: UNKNOWN
Classifier: Programming Language :: Python :: 3
Classifier: License :: OSI Approved :: MIT License
Classifier: Operating System :: OS Independent
